humanloop/__init__.py
humanloop/api_client.py
humanloop/api_response.py
humanloop/client.py
humanloop/configuration.py
humanloop/exceptions.py
humanloop/exceptions_base.py
humanloop/request_after_hook.py
humanloop/request_before_hook.py
humanloop/rest.py
humanloop/schemas.py
humanloop/validation_metadata.py
humanloop/apis/__init__.py
humanloop/apis/path_to_api.py
humanloop/apis/tag_to_api.py
humanloop/apis/paths/__init__.py
humanloop/apis/paths/chat.py
humanloop/apis/paths/experiments_experiment_id.py
humanloop/apis/paths/experiments_experiment_id_model_config.py
humanloop/apis/paths/feedback.py
humanloop/apis/paths/generate.py
humanloop/apis/paths/logs.py
humanloop/apis/paths/model_configs.py
humanloop/apis/paths/model_configs_id.py
humanloop/apis/paths/projects.py
humanloop/apis/paths/projects_id.py
humanloop/apis/paths/projects_id_active_experiment.py
humanloop/apis/paths/projects_id_active_model_config.py
humanloop/apis/paths/projects_id_export.py
humanloop/apis/paths/projects_id_feedback_types.py
humanloop/apis/paths/projects_id_model_config.py
humanloop/apis/paths/projects_id_model_configs.py
humanloop/apis/paths/projects_project_id_experiments.py
humanloop/apis/tags/__init__.py
humanloop/apis/tags/experiments_api.py
humanloop/apis/tags/feedback_api.py
humanloop/apis/tags/generate_api.py
humanloop/apis/tags/logs_api.py
humanloop/apis/tags/model_configs_api.py
humanloop/apis/tags/projects_api.py
humanloop/model/__init__.py
humanloop/model/base_metric_response.py
humanloop/model/categorical_feedback_label.py
humanloop/model/chat_data_response.py
humanloop/model/chat_message.py
humanloop/model/chat_model_config_request.py
humanloop/model/chat_request.py
humanloop/model/chat_response.py
humanloop/model/chat_role.py
humanloop/model/create_experiment_request.py
humanloop/model/create_log_response.py
humanloop/model/create_project_request.py
humanloop/model/data_response.py
humanloop/model/experiment_chat.py
humanloop/model/experiment_generate.py
humanloop_python_sdk-3.3.0.dist-info/LICENSE
humanloop_python_sdk-3.3.0.dist-info/METADATA
humanloop_python_sdk-3.3.0.dist-info/WHEEL
humanloop_python_sdk-3.3.0.dist-info/top_level.txt
humanloop_python_sdk-3.3.0.dist-info/RECORD
