Metadata-Version: 2.1
Name: humanloop-python-sdk
Version: 3.3.0
Summary: Humanloop API
Home-page: https://github.com/konfig-dev/humanloop-sdks/tree/main/v3/python
Author: Konfig
Author-email: engineering@konfigthis.com
License: MIT
Keywords: Konfig,Humanloop API
Requires-Python: >=3.7
License-File: LICENSE
Requires-Dist: certifi (>=2022.12.7)
Requires-Dist: frozendict (~=2.3.4)
Requires-Dist: python-dateutil (~=2.7.0)
Requires-Dist: setuptools (>=21.0.0)
Requires-Dist: typing-extensions (~=4.3.0)
Requires-Dist: urllib3 (~=1.26.7)
Requires-Dist: validators (~=0.20.0)
